when.py
pywhen-0.11.2.dist-info/LICENSE
pywhen-0.11.2.dist-info/METADATA
pywhen-0.11.2.dist-info/WHEEL
pywhen-0.11.2.dist-info/top_level.txt
pywhen-0.11.2.dist-info/RECORD
