Metadata-Version: 2.1
Name: pywhen
Version: 0.11.2
Summary: Collection of random python tools and utilities 
Home-page: https://github.com/cltrudeau/wrench
Author: Christopher Trudeau
Author-email: ctrudeau+pypi@arsensa.com
License: MIT
Keywords: tools
Classifier: Development Status :: 4 - Beta
Classifier: Environment :: Web Environment
Classifier: Intended Audience :: Developers
Classifier: License :: OSI Approved :: MIT License
Classifier: Operating System :: OS Independent
Classifier: Programming Language :: Python :: 3.8
Classifier: Programming Language :: Python :: 3.9
Classifier: Programming Language :: Python :: 3.10
Classifier: Programming Language :: Python :: 3.11
Classifier: Topic :: Software Development :: Libraries :: Application Frameworks
Classifier: Topic :: Software Development :: Libraries :: Python Modules
License-File: LICENSE
